onesocial_django/__init__.py
onesocial_django/admin.py
onesocial_django/models.py
onesocial_django/settings.py
onesocial_django/urls.py
onesocial_django/utils.py
onesocial_django/views.py
onesocial_django/locale/ru/LC_MESSAGES/django.po
onesocial_django/migrations/0001_initial.py
onesocial_django/migrations/0002_auto_20201021_0912.py
onesocial_django/migrations/0003_auto_20201021_0928.py
onesocial_django/migrations/__init__.py
onesocial_django-1.0.0.dist-info/METADATA
onesocial_django-1.0.0.dist-info/WHEEL
onesocial_django-1.0.0.dist-info/top_level.txt
onesocial_django-1.0.0.dist-info/RECORD
