Metadata-Version: 2.1
Name: onesocial-django
Version: 1.0.0
Summary: Приложение Django для входа через соцсети с помощью OneSocial API
Home-page: https://github.com/onesocial-dev/onesocial-django
Author: Oleg Yamnikov
Author-email: oyam@oxymeal.ru
License: MIT
Platform: UNKNOWN
Classifier: License :: OSI Approved :: MIT License
Classifier: Programming Language :: Python :: 3
Classifier: Programming Language :: Python :: 3.6
